README.rst
setup.cfg
setup.py
slack_cli.egg-info/PKG-INFO
slack_cli.egg-info/SOURCES.txt
slack_cli.egg-info/dependency_links.txt
slack_cli.egg-info/entry_points.txt
slack_cli.egg-info/requires.txt
slack_cli.egg-info/top_level.txt
slackcli/__init__.py
slackcli/cli.py
slackcli/emoji.json
slackcli/emoji.py
slackcli/errors.py
slackcli/messaging.py
slackcli/names.py
slackcli/slack.py
slackcli/stream.py
slackcli/token.py
slackcli/ui.py