Metadata-Version: 2.1
Name: slack-cli
Version: 2.2.8
Summary: Slack CLI for productive developers
Home-page: https://github.com/regisb/slack-cli
Author: Régis Behmo
Author-email: nospam@behmo.com
License: MIT
Platform: UNKNOWN
Classifier: Programming Language :: Python
Classifier: Programming Language :: Python :: 3.3
Classifier: Programming Language :: Python :: 3.4
Classifier: Programming Language :: Python :: 3.5
Classifier: Programming Language :: Python :: 3.6
Provides-Extra: development
